object_trace/__init__.py
object_trace/object_trace.py
object_trace/py_stack.py
object_trace-0.1.2.dist-info/METADATA
object_trace-0.1.2.dist-info/WHEEL
object_trace-0.1.2.dist-info/top_level.txt
object_trace-0.1.2.dist-info/RECORD
