Metadata-Version: 2.1
Name: object-trace
Version: 0.1.2
Summary: Trace every use of selected objects
Home-page: https://github.com/verinov/object-trace
Author: Alexander Verinov
Author-email: alex@verinov.dev
License: MIT
Platform: UNKNOWN
Classifier: License :: OSI Approved :: MIT License
Classifier: Programming Language :: Python :: 3
Classifier: Programming Language :: Python :: 3.7
Classifier: Programming Language :: Python :: 3.8
Classifier: Programming Language :: Python :: 3.9
Classifier: Programming Language :: Python :: 3.10
Classifier: Programming Language :: Python :: Implementation :: CPython
